{
  "cities": [
    {
      "name": " Subotica"
    },
    {
      "name": "Bačka Topola"
    },
    {
      "name": "Mali Iđoš"
    },
    {
      "name": " Zrenjanin"
    },
    {
      "name": "Novi Bečej"
    },
    {
      "name": "Nova Crnja"
    },
    {
      "name": "Žitište"
    },
    {
      "name": "Sečanj"
    },
    {
      "name": "Kanjiža"
    },
    {
      "name": "Senta"
    },
    {
      "name": "Ada"
    },
    {
      "name": "Čoka"
    },
    {
      "name": "Novi Kneževac"
    },
    {
      "name": " Kikinda"
    },
    {
      "name": " Pančevo"
    },
    {
      "name": "Plandište"
    },
    {
      "name": "Opovo"
    },
    {
      "name": "Kovačica"
    },
    {
      "name": "Alibunar"
    },
    {
      "name": " Vršac"
    },
    {
      "name": "Bela Crkva"
    },
    {
      "name": "Kovin"
    },
    {
      "name": " Sombor"
    },
    {
      "name": "Apatin"
    },
    {
      "name": "Odžaci"
    },
    {
      "name": "Kula"
    },
    {
      "name": "Bač"
    },
    {
      "name": "Bačka Palanka"
    },
    {
      "name": "Bački Petrovac"
    },
    {
      "name": "Beočin"
    },
    {
      "name": "Bečej"
    },
    {
      "name": "Vrbas"
    },
    {
      "name": "Žabalj"
    },
    {
      "name": " Novi Sad"
    },
    {
      "name": "Srbobran"
    },
    {
      "name": "Temerin"
    },
    {
      "name": "Titel"
    },
    {
      "name": "Sremski Karlovci"
    },
    {
      "name": " Sremska Mitrovica"
    },
    {
      "name": "Sremska Mitrovica"
    },
    {
      "name": "Šid"
    },
    {
      "name": "Inđija"
    },
    {
      "name": "Irig"
    },
    {
      "name": "Ruma"
    },
    {
      "name": "Stara Pazova"
    },
    {
      "name": "Pećinci"
    },
    {
      "name": " Šabac"
    },
    {
      "name": " Loznica"
    },
    {
      "name": "Bogatić"
    },
    {
      "name": "Vladimirci"
    },
    {
      "name": "Koceljeva"
    },
    {
      "name": "Mali Zvornik"
    },
    {
      "name": "Krupanj"
    },
    {
      "name": "Ljubovija"
    },
    {
      "name": " Valjevo"
    },
    {
      "name": "Osečina"
    },
    {
      "name": "Ub"
    },
    {
      "name": "Lajkovac"
    },
    {
      "name": "Mionica"
    },
    {
      "name": "Ljig"
    },
    {
      "name": " Smederevo"
    },
    {
      "name": "Smederevska Palanka"
    },
    {
      "name": "Velika Plana"
    },
    {
      "name": " Požarevac"
    },
    {
      "name": "Veliko Gradište"
    },
    {
      "name": "Golubac"
    },
    {
      "name": "Malo Crniće"
    },
    {
      "name": "Žabari"
    },
    {
      "name": "Petrovac na Mlavi"
    },
    {
      "name": "Kučevo"
    },
    {
      "name": "Žagubica"
    },
    {
      "name": " Kragujevac"
    },
    {
      "name": "Aranđelovac"
    },
    {
      "name": "Topola"
    },
    {
      "name": "Rača"
    },
    {
      "name": "Batočina"
    },
    {
      "name": "Knić"
    },
    {
      "name": "Lapovo"
    },
    {
      "name": " Jagodina"
    },
    {
      "name": "Ćuprija"
    },
    {
      "name": "Paraćin"
    },
    {
      "name": "Svilajnac"
    },
    {
      "name": "Despotovac"
    },
    {
      "name": "Rekovac"
    },
    {
      "name": " Beograd"
    },
    {
      "name": "Bor"
    },
    {
      "name": "Kladovo"
    },
    {
      "name": "Majdanpek"
    },
    {
      "name": "Negotin"
    },
    {
      "name": " Zaječar"
    },
    {
      "name": "Boljevac"
    },
    {
      "name": "Knjaževac"
    },
    {
      "name": "Sokobanja"
    },
    {
      "name": " Užice"
    },
    {
      "name": "Bajina Bašta"
    },
    {
      "name": "Kosjerić"
    },
    {
      "name": "Požega"
    },
    {
      "name": "Čajetina"
    },
    {
      "name": "Arilje"
    },
    {
      "name": "Priboj"
    },
    {
      "name": "Nova Varoš"
    },
    {
      "name": "Prijepolje"
    },
    {
      "name": "Sjenica"
    },
    {
      "name": " Čačak"
    },
    {
      "name": "Gornji Milanovac"
    },
    {
      "name": "Lučani"
    },
    {
      "name": "Ivanjica"
    },
    {
      "name": " Kraljevo"
    },
    {
      "name": " Novi Pazar"
    },
    {
      "name": "Vrnjačka Banja"
    },
    {
      "name": "Raška"
    },
    {
      "name": "Tutin"
    },
    {
      "name": " Kruševac"
    },
    {
      "name": "Varvarin"
    },
    {
      "name": "Trstenik"
    },
    {
      "name": "Ćićevac"
    },
    {
      "name": "Aleksandrovac"
    },
    {
      "name": "Brus"
    },
    {
      "name": " Niš"
    },
    {
      "name": "Aleksinac"
    },
    {
      "name": "Svrljig"
    },
    {
      "name": "Merošina"
    },
    {
      "name": "Ražanj"
    },
    {
      "name": "Doljevac"
    },
    {
      "name": "Gadžin Han"
    },
    {
      "name": "Prokuplje"
    },
    {
      "name": "Blace"
    },
    {
      "name": "Kuršumlija"
    },
    {
      "name": "Žitorađa"
    },
    {
      "name": " Pirot"
    },
    {
      "name": "Bela Palanka"
    },
    {
      "name": "Babušnica"
    },
    {
      "name": "Dimitrovgrad"
    },
    {
      "name": " Leskovac"
    },
    {
      "name": "Bojnik"
    },
    {
      "name": "Lebane"
    },
    {
      "name": "Medveđa"
    },
    {
      "name": "Vlasotince"
    },
    {
      "name": "Crna Trava"
    },
    {
      "name": " Vranje"
    },
    {
      "name": "Vladičin Han"
    },
    {
      "name": "Surdulica"
    },
    {
      "name": "Bosilegrad"
    },
    {
      "name": "Trgovište"
    },
    {
      "name": "Bujanovac"
    },
    {
      "name": "Preševo"
    }
  ],
  "users": [
    {
      "id": 1,
      "username": "danoi",
      "password": "danoi123",
      "email": "danoi@gmail.com"
    },
    {
      "id": 2,
      "username": "milenica",
      "password": "milea123",
      "email": "milena@mail.com"
    },
    {
      "id": 3,
      "username": "mimi",
      "password": "mi123",
      "email": "mimi@mail.com"
    },
    {
      "id": 4,
      "username": "tikica",
      "password": "tiki123",
      "email": "tika@mail.com"
    },
    {
      "id": 5,
      "username": "kate",
      "password": "kate123",
      "email": "kate@mail.com"
    },
    {
      "id": 6,
      "username": "nata",
      "password": "nata123",
      "email": "nata@mail.com"
    },
    {
      "id": 7,
      "username": "filip",
      "password": "filip123",
      "email": "filip@mail.com"
    },
    {
      "username": "danoi123",
      "password": "test123",
      "email": "test@mail.com",
      "id": 35
    }
  ],
  "events": [
    {
      "id": 1,
      "headline": "Garbage collecting",
      "description": "Sed ut perspiciatis unde omnis iste natus error sit voluptatem accusantium doloremque laudantium, totam rem aperiam, eaque ipsa quae ab illo inventore veritatis et quasi architecto beatae vitae dicta sunt explicabo. Nemo enim ipsam voluptatem quia voluptas sit aspernatur aut odit aut fugit, sed quia consequuntur magni dolores eos qui ratione voluptatem sequi nesciunt. Neque porro quisquam est, qui dolorem ipsum quia dolor sit amet, consectetur, adipisci velit, sed quia non numquam eius modi tempora incidunt ut labore et dolore magnam aliquam quaerat voluptatem. Ut enim ad minima veniam, quis nostrum exercitationem ullam corporis suscipit laboriosam, nisi ut aliquid ex ea commodi consequatur? Quis autem vel eum iure reprehenderit qui in ea voluptate velit esse quam nihil molestiae consequatur, vel illum qui dolorem eum fugiat quo voluptas nulla pariatur? Lorem ipsum dolor sit amet, consectetur adipiscing elit, sed do eiusmod tempor incididunt ut labore et dolore magna aliqua. Ut enim ad minim veniam, quis nostrud exercitation ullamco laboris nisi ut aliquip ex ea commodo consequat. Duis aute irure dolor in reprehenderit in voluptate velit esse cillum dolore eu fugiat nulla pariatur. Excepteur sint occaecat cupidatat non proident, sunt in culpa qui officia deserunt mollit anim id est laborum.",
      "date": "2019-08-20",
      "address": "Somborska",
      "city": "Niš",
      "img": "../assets/img/event2.jpg",
      "maxCapacity": 150,
      "time": "22:20",
      "numberOfPeopleComing": 13
    },
    {
      "id": 2,
      "headline": "Garbage collecting",
      "description": "Sed ut perspiciatis unde omnis iste natus error sit voluptatem accusantium doloremque laudantium, totam rem aperiam, eaque ipsa quae ab illo inventore veritatis et quasi architecto beatae vitae dicta sunt explicabo. Nemo enim ipsam voluptatem quia voluptas sit aspernatur aut odit aut fugit, sed quia consequuntur magni dolores eos qui ratione voluptatem sequi nesciunt. Neque porro quisquam est, qui dolorem ipsum quia dolor sit amet, consectetur, adipisci velit, sed quia non numquam eius modi tempora incidunt ut labore et dolore magnam aliquam quaerat voluptatem. Ut enim ad minima veniam, quis nostrum exercitationem ullam corporis suscipit laboriosam, nisi ut aliquid ex ea commodi consequatur? Quis autem vel eum iure reprehenderit qui in ea voluptate velit esse quam nihil molestiae consequatur, vel illum qui dolorem eum fugiat quo voluptas nulla pariatur? Lorem ipsum dolor sit amet, consectetur adipiscing elit, sed do eiusmod tempor incididunt ut labore et dolore magna aliqua. Ut enim ad minim veniam, quis nostrud exercitation ullamco laboris nisi ut aliquip ex ea commodo consequat. Duis aute irure dolor in reprehenderit in voluptate velit esse cillum dolore eu fugiat nulla pariatur. Excepteur sint occaecat cupidatat non proident, sunt in culpa qui officia deserunt mollit anim id est laborum.",
      "date": "2019-10-03",
      "address": "Somborska",
      "city": "Niš",
      "img": "../assets/img/event1.jpg",
      "maxCapacity": 150,
      "time": "22:20",
      "numberOfPeopleComing": 9
    },
    {
      "id": 3,
      "headline": "Garbage collecting",
      "description": "Sed ut perspiciatis unde omnis iste natus error sit voluptatem accusantium doloremque laudantium, totam rem aperiam, eaque ipsa quae ab illo inventore veritatis et quasi architecto beatae vitae dicta sunt explicabo. Nemo enim ipsam voluptatem quia voluptas sit aspernatur aut odit aut fugit, sed quia consequuntur magni dolores eos qui ratione voluptatem sequi nesciunt. Neque porro quisquam est, qui dolorem ipsum quia dolor sit amet, consectetur, adipisci velit, sed quia non numquam eius modi tempora incidunt ut labore et dolore magnam aliquam quaerat voluptatem. Ut enim ad minima veniam, quis nostrum exercitationem ullam corporis suscipit laboriosam, nisi ut aliquid ex ea commodi consequatur? Quis autem vel eum iure reprehenderit qui in ea voluptate velit esse quam nihil molestiae consequatur, vel illum qui dolorem eum fugiat quo voluptas nulla pariatur? Lorem ipsum dolor sit amet, consectetur adipiscing elit, sed do eiusmod tempor incididunt ut labore et dolore magna aliqua. Ut enim ad minim veniam, quis nostrud exercitation ullamco laboris nisi ut aliquip ex ea commodo consequat. Duis aute irure dolor in reprehenderit in voluptate velit esse cillum dolore eu fugiat nulla pariatur. Excepteur sint occaecat cupidatat non proident, sunt in culpa qui officia deserunt mollit anim id est laborum.",
      "date": "2019-06-27",
      "address": "Somborska",
      "city": "Niš",
      "img": "../assets/img/event3.jpg",
      "maxCapacity": 150,
      "time": "22:20",
      "numberOfPeopleComing": 10
    },
    {
      "id": 4,
      "headline": "Garbage collecting",
      "description": "Lorem ipsum dolor sit amet, consectetur adipiscing elit, sed do eiusmod tempor incididunt ut labore et dolore magna aliqua. Ut enim ad minim veniam, quis nostrud exercitation ullamco laboris nisi ut aliquip ex ea commodo consequat. Duis aute irure dolor in reprehenderit in voluptate velit esse cillum dolore eu fugiat nulla pariatur. Excepteur sint occaecat cupidatat non proident, sunt in culpa qui officia deserunt mollit anim id est laborum.",
      "date": "2019-06-20",
      "address": "Vozdova 5",
      "city": "Niš",
      "img": "../assets/img/event4.jpg",
      "maxCapacity": 10,
      "time": "22:20",
      "numberOfPeopleComing": 10
    },
    {
      "id": 5,
      "headline": "Garbage collecting",
      "description": "Lorem ipsum dolor sit amet, consectetur adipiscing elit, sed do eiusmod tempor incididunt ut labore et dolore magna aliqua. Ut enim ad minim veniam, quis nostrud exercitation ullamco laboris nisi ut aliquip ex ea commodo consequat. Duis aute irure dolor in reprehenderit in voluptate velit esse cillum dolore eu fugiat nulla pariatur. Excepteur sint occaecat cupidatat non proident, sunt in culpa qui officia deserunt mollit anim id est laborum.",
      "date": "2019-12-05",
      "address": "Zelengorska 23",
      "city": "Niš",
      "img": "../assets/img/event5.jpg",
      "maxCapacity": 150,
      "time": "22:20",
      "numberOfPeopleComing": 10
    },
    {
      "id": 6,
      "headline": "Garbage collecting",
      "description": "Lorem ipsum dolor sit amet, consectetur adipiscing elit, sed do eiusmod tempor incididunt ut labore et dolore magna aliqua. Ut enim ad minim veniam, quis nostrud exercitation ullamco laboris nisi ut aliquip ex ea commodo consequat. Duis aute irure dolor in reprehenderit in voluptate velit esse cillum dolore eu fugiat nulla pariatur. Excepteur sint occaecat cupidatat non proident, sunt in culpa qui officia deserunt mollit anim id est laborum.",
      "date": "2019-06-20",
      "address": "Bulevar Nemanjica",
      "city": "Niš",
      "img": "../assets/img/event6.jpeg",
      "maxCapacity": 150,
      "time": "22:20",
      "numberOfPeopleComing": 10
    },
    {
      "id": 7,
      "headline": "Garbage collecting",
      "description": "Lorem ipsum dolor sit amet, consectetur adipiscing elit, sed do eiusmod tempor incididunt ut labore et dolore magna aliqua. Ut enim ad minim veniam, quis nostrud exercitation ullamco laboris nisi ut aliquip ex ea commodo consequat. Duis aute irure dolor in reprehenderit in voluptate velit esse cillum dolore eu fugiat nulla pariatur. Excepteur sint occaecat cupidatat non proident, sunt in culpa qui officia deserunt mollit anim id est laborum.",
      "date": "2019-06-20",
      "address": "Cirila i Metodija 5",
      "city": "Niš",
      "img": "../assets/img/event7.jpg",
      "maxCapacity": 150,
      "time": "22:20",
      "numberOfPeopleComing": 10
    },
    {
      "maxCapacity": 152,
      "numberOfPeopleComing": 1,
      "id": 37,
      "headline": "New Event In Town",
      "description": "This will be the greatest event you will EVER visit in your lifetime. There will be great music and loads of fun! We are expecting you!!!!",
      "address": "Somborska",
      "date": "2019-06-20",
      "city": "Niš",
      "time": "22:20",
      "img": "../assets/img/events.jpg"
    },
    {
      "maxCapacity": 200,
      "numberOfPeopleComing": 1,
      "id": 82,
      "headline": "FUN FUN FUN",
      "description": "You will have a lot of fun at out event!",
      "address": "Zelengorska",
      "date": "2019-06-29",
      "city": "Niš",
      "time": "16:00",
      "img": "../assets/img/event12.jpg"
    },
    {
      "id": 568,
      "headline": "PozitivNI",
      "description": "Ako vam neko govori o najposećenijoj manifestaciji u južnoj Srbiji, o jedinom street art festivalu koji spaja sve oblasti umetnosti, znajte da vam priča o festivalu PozitivNI! U toj priči o nama, možete čuti i da je ovaj festival nastao kako bi probudio duh urbanog Niša koji je devedestih godina prošlog veka ostao zakopan negde u Dušanovoj, u ulici koja pamti najbolje svirke u gradu. PozitivNI su tu da taj duh vrate gradu, u njegovu slavu, i na njegovoj slavi! Zapravo, termin održavanja festivala određen je tako da se poklapa sa datumom gradske slave-dana Svetog cara Konstantina i carice Jelene.\n\nOve godine, festival će po prvi put trajati 4 dana. Spajaćemo klasicizam i alternativu, preplitati sport i muziku, pozorište i izlete, kroz interakciju ćemo učiti o svetu umetnosti, a onda pravu umetnost i slušati! A sadržaji, pitate se, kome su namenjeni? PozitivNI su tu za svakog, od 1 do 101! Ovo je mesto gde će svaka osoba naći nešto njoj zanimljivo, lepo i vredno divljenja. Dobrodošli!",
      "address": "Park Cair",
      "date": "2019-06-24",
      "city": "Niš",
      "maxCapacity": 500,
      "img": "../assets/img/20190501_160027.jpg",
      "time": "16:00"
    }
  ],
  "eventsInteresstedIn": [
    {
      "id": 2,
      "eventId": 37,
      "userId": 6,
      "isComming": true
    },
    {
      "eventId": "82",
      "userId": 6,
      "isComming": true,
      "id": 218
    },
    {
      "eventId": "4",
      "userId": 6,
      "isComming": true,
      "id": 422
    }
  ]
}